django_website_showroom-0.4.0.dist-info/DESCRIPTION.rst
django_website_showroom-0.4.0.dist-info/METADATA
django_website_showroom-0.4.0.dist-info/RECORD
django_website_showroom-0.4.0.dist-info/WHEEL
django_website_showroom-0.4.0.dist-info/metadata.json
django_website_showroom-0.4.0.dist-info/top_level.txt
website_showroom/__init__.py
website_showroom/admin.py
website_showroom/feeds.py
website_showroom/models.py
website_showroom/search_indexes.py
website_showroom/tests.py
website_showroom/urls.py
website_showroom/views.py
website_showroom/migrations/0001_initial.py
website_showroom/migrations/__init__.py
website_showroom/static/.DS_Store
website_showroom/static/content-1.0.0.css
website_showroom/static/content-1.0.1.css
website_showroom/static/content.css
website_showroom/static/lib/.DS_Store
website_showroom/static/lib/font-awesome.css
website_showroom/static/lib/font/fontawesome-webfont.eot
website_showroom/static/lib/font/fontawesome-webfont.svg
website_showroom/static/lib/font/fontawesome-webfont.ttf
website_showroom/static/lib/font/fontawesome-webfont.woff
website_showroom/static/world/ad.png
website_showroom/static/world/ad.woa.png
website_showroom/static/world/ae.png
website_showroom/static/world/af.png
website_showroom/static/world/ag.png
website_showroom/static/world/ai.png
website_showroom/static/world/al.png
website_showroom/static/world/am.png
website_showroom/static/world/an.png
website_showroom/static/world/ao.png
website_showroom/static/world/aq.png
website_showroom/static/world/ar.png
website_showroom/static/world/ar.woa.png
website_showroom/static/world/as.png
website_showroom/static/world/at.png
website_showroom/static/world/au.png
website_showroom/static/world/aw.png
website_showroom/static/world/ax.png
website_showroom/static/world/az.png
website_showroom/static/world/ba.png
website_showroom/static/world/bb.png
website_showroom/static/world/bd.png
website_showroom/static/world/be.png
website_showroom/static/world/bf.png
website_showroom/static/world/bg.png
website_showroom/static/world/bh.png
website_showroom/static/world/bi.png
website_showroom/static/world/bj.png
website_showroom/static/world/bl.loc.png
website_showroom/static/world/bl.png
website_showroom/static/world/bm.png
