Metadata-Version: 2.0
Name: django-website-showroom
Version: 0.4.0
Summary: General purpose showroom for presenting a collection of categorized websites
Home-page: https://github.com/holgerd77/django-website-showroom/
Author: Holger Drewes
Author-email: Holger.Drewes@gmail.com
License: BSD License
Platform: OS Independent
Classifier: Development Status :: 3 - Alpha
Classifier: Environment :: Web Environment
Classifier: Framework :: Django
Classifier: Intended Audience :: Developers
Classifier: License :: OSI Approved :: BSD License
Classifier: Operating System :: OS Independent
Classifier: Programming Language :: Python
Classifier: Topic :: Utilities
Requires-Dist: Django (<2.0,>=1.11)
Requires-Dist: Pillow
Requires-Dist: Whoosh (<2.8,>=2.7)
Requires-Dist: django-haystack (>=2.6,<2.7)
